tana2tree/__init__.py
tana2tree/tana2tree.py
tana2tree/tree.py
tana2tree-1.1.19.dist-info/LICENSE
tana2tree-1.1.19.dist-info/METADATA
tana2tree-1.1.19.dist-info/WHEEL
tana2tree-1.1.19.dist-info/top_level.txt
tana2tree-1.1.19.dist-info/RECORD
