Metadata-Version: 2.1
Name: tana2tree
Version: 1.1.19
Summary: Parses Tanagra description into usable formats.
Home-page: https://github.com/reevesba/tana2tree
Author: Bradley Reeves
Author-email: bradleyaaronreeeves@gmail.com
License: UNKNOWN
Platform: UNKNOWN
Classifier: Programming Language :: Python :: 3
Classifier: License :: OSI Approved :: MIT License
Classifier: Operating System :: OS Independent
Requires-Python: >=3.6
